Workbook

Sheet EMPLOYEE MASTER DATA
A1: EMPLOYEE MASTER DATA
A3: Emp No | B3: Employee Name | C3: Location | D3: Department | E3: Designation | F3: Basic Salary
A4: EMP001 | B4: Vijay V | C4: Hyderabad | D4: Production | E4: Production Executive | F4: 29000
A5: EMP002 | B5: Sathish V | C5: Hyderabad | D5: Production | E5: Shift Incharge | F5: 46500
A6: EMP003 | B6: Aravind B | C6: Chennai | D6: Business Development | E6: Senior Business Development Executive | F6: 44500
A7: EMP004 | B7: Ramesh Kumar | C7: Bengaluru | D7: Front Office | E7: Receptionist | F7: 20500
A8: EMP005 | B8: Naveen Kumar | C8: Coimbatore | D8: Front Office | E8: Front Office Executive | F8: 29000
A9: EMP006 | B9: Karthik T | C9: Bengaluru | D9: Admin | E9: Admin Manager | F9: 53500
A10: EMP007 | B10: Arun B | C10: Kochi | D10: Admin | E10: Office Coordinator | F10: 25500
A11: EMP008 | B11: Sathish G | C11: Kochi | D11: Accounts | E11: Accountant | F11: 27500
A12: EMP009 | B12: Yuvaraj Babu | C12: Noida | D12: Sales | E12: Senior Sales Executive | F12: 43500
A13: EMP010 | B13: Sanjay G | C13: Delhi | D13: Procurement | E13: Buyer | F13: 45000
A14: EMP011 | B14: Vijay T | C14: Chennai | D14: Accounts | E14: Finance Executive | F14: 36000
A15: EMP012 | B15: Mohan M | C15: Chennai | D15: Admin | E15: Office Administrator | F15: 28000
... A303: EMP300 | B303: Ganesh Narayanan | C303: Hyderabad | D303: Maintenance | E303: Maintenance Supervisor | F303: 42000

Sheet DAY ATTENDANCE
A1: DAY ATTENDANCE - 01/02/2026
A2: Employee Number | B2: Name | C2: Location | D2: Department | E2: Designation | F2: In Time | G2: Out Time | H2: Work Hours | I2: Status | J2: Late | K2: Remarks
A3: {=_xlfn.SORTBY('EMPLOYEE MASTER DATA'!A4:E303,'EMPLOYEE MASTER DATA'!D4:D303,1)} -> EMP008 | B3: Sathish G | C3: Kochi | D3: Accounts | E3: Accountant | F3: 0.38888889 | G3: 0.78888889 | H3: =IF(OR(F3="",G3=""),0,G3-F3-TIME(1,0,0)) -> 0.35833333 | I3: =IF(F3="","Absent",IF(F3>TIME(9,30,0),"Late","Present")) -> Present | J3: =IF(F3="","",IF(F3<=TIME(9,30,0),0,F3-TIME(9,30,0))) -> 0 | K3: =IF(AND(F3<>"",G3=""),"On Duty","")
A4: EMP011 | B4: Vijay T | C4: Chennai | D4: Accounts | E4: Finance Executive | F4: 0.38680556 | G4: 0.78263889 | H4: =IF(OR(F4="",G4=""),0,G4-F4-TIME(1,0,0)) -> 0.35416667 | I4: =IF(F4="","Absent",IF(F4>TIME(9,30,0),"Late","Present")) -> Present | J4: =IF(F4="","",IF(F4<=TIME(9,30,0),0,F4-TIME(9,30,0))) -> 0 | K4: =IF(AND(F4<>"",G4=""),"On Duty","")
A5: EMP013 | B5: Madhan Selvam | C5: Mumbai | D5: Accounts | E5: Senior Accountant | F5: 0.40625 | H5: =IF(OR(F5="",G5=""),0,G5-F5-TIME(1,0,0)) -> 0 | I5: =IF(F5="","Absent",IF(F5>TIME(9,30,0),"Late","Present")) -> Late | J5: =IF(F5="","",IF(F5<=TIME(9,30,0),0,F5-TIME(9,30,0))) -> 0.010416667 | K5: =IF(AND(F5<>"",G5=""),"On Duty","") -> On Duty
A6: EMP029 | B6: Harish N | C6: Pune | D6: Accounts | E6: Accountant | F6: 0.38680556 | G6: 0.78125 | H6: =IF(OR(F6="",G6=""),0,G6-F6-TIME(1,0,0)) -> 0.35277778 | I6: =IF(F6="","Absent",IF(F6>TIME(9,30,0),"Late","Present")) -> Present | J6: =IF(F6="","",IF(F6<=TIME(9,30,0),0,F6-TIME(9,30,0))) -> 0 | K6: =IF(AND(F6<>"",G6=""),"On Duty","")
A7: EMP042 | B7: Prakash S | C7: Coimbatore | D7: Accounts | E7: Accounts Manager | F7: 0.39305556 | H7: =IF(OR(F7="",G7=""),0,G7-F7-TIME(1,0,0)) -> 0 | I7: =IF(F7="","Absent",IF(F7>TIME(9,30,0),"Late","Present")) -> Present | J7: =IF(F7="","",IF(F7<=TIME(9,30,0),0,F7-TIME(9,30,0))) -> 0 | K7: =IF(AND(F7<>"",G7=""),"On Duty","") -> On Duty
A8: EMP050 | B8: Manoj P | C8: Chennai | D8: Accounts | E8: Senior Accountant | F8: 0.39444444 | G8: 0.78472222 | H8: =IF(OR(F8="",G8=""),0,G8-F8-TIME(1,0,0)) -> 0.34861111 | I8: =IF(F8="","Absent",IF(F8>TIME(9,30,0),"Late","Present")) -> Present | J8: =IF(F8="","",IF(F8<=TIME(9,30,0),0,F8-TIME(9,30,0))) -> 0 | K8: =IF(AND(F8<>"",G8=""),"On Duty","")
A9: EMP067 | B9: Vignesh Raja | C9: Mumbai | D9: Accounts | E9: Finance Executive | F9: 0.38819444 | H9: =IF(OR(F9="",G9=""),0,G9-F9-TIME(1,0,0)) -> 0 | I9: =IF(F9="","Absent",IF(F9>TIME(9,30,0),"Late","Present")) -> Present | J9: =IF(F9="","",IF(F9<=TIME(9,30,0),0,F9-TIME(9,30,0))) -> 0 | K9: =IF(AND(F9<>"",G9=""),"On Duty","") -> On Duty
A10: EMP069 | B10: Yogesh M | C10: Bengaluru | D10: Accounts | E10: Accounts Manager | F10: 0.40416667 | G10: 0.77708333 | H10: =IF(OR(F10="",G10=""),0,G10-F10-TIME(1,0,0)) -> 0.33125 | I10: =IF(F10="","Absent",IF(F10>TIME(9,30,0),"Late","Present")) -> Late | J10: =IF(F10="","",IF(F10<=TIME(9,30,0),0,F10-TIME(9,30,0))) -> 0.0083333333 | K10: =IF(AND(F10<>"",G10=""),"On Duty","")
A11: EMP070 | B11: Rahul Krishnan | C11: Chennai | D11: Accounts | E11: Accounts Manager | F11: 0.40208333 | H11: =IF(OR(F11="",G11=""),0,G11-F11-TIME(1,0,0)) -> 0 | I11: =IF(F11="","Absent",IF(F11>TIME(9,30,0),"Late","Present")) -> Late | J11: =IF(F11="","",IF(F11<=TIME(9,30,0),0,F11-TIME(9,30,0))) -> 0.00625 | K11: =IF(AND(F11<>"",G11=""),"On Duty","") -> On Duty
A12: EMP072 | B12: Sanjay S | C12: Bengaluru | D12: Accounts | E12: Finance Executive | F12: 0.38263889 | G12: 0.77916667 | H12: =IF(OR(F12="",G12=""),0,G12-F12-TIME(1,0,0)) -> 0.35486111 | I12: =IF(F12="","Absent",IF(F12>TIME(9,30,0),"Late","Present")) -> Present | J12: =IF(F12="","",IF(F12<=TIME(9,30,0),0,F12-TIME(9,30,0))) -> 0 | K12: =IF(AND(F12<>"",G12=""),"On Duty","")
A13: EMP076 | B13: Prakash T | C13: Pune | D13: Accounts | E13: Accountant | F13: 0.40069444 | G13: 0.77083333 | H13: =IF(OR(F13="",G13=""),0,G13-F13-TIME(1,0,0)) -> 0.32847222 | I13: =IF(F13="","Absent",IF(F13>TIME(9,30,0),"Late","Present")) -> Late | J13: =IF(F13="","",IF(F13<=TIME(9,30,0),0,F13-TIME(9,30,0))) -> 0.0048611111 | K13: =IF(AND(F13<>"",G13=""),"On Duty","")
A14: EMP093 | B14: Suresh Raj | C14: Mumbai | D14: Accounts | E14: Accounts Manager | H14: =IF(OR(F14="",G14=""),0,G14-F14-TIME(1,0,0)) -> 0 | I14: =IF(F14="","Absent",IF(F14>TIME(9,30,0),"Late","Present")) -> Absent | J14: =IF(F14="","",IF(F14<=TIME(9,30,0),0,F14-TIME(9,30,0))) | K14: =IF(AND(F14<>"",G14=""),"On Duty","")
A15: EMP099 | B15: Yuvaraj N | C15: Kochi | D15: Accounts | E15: Accounts Manager | F15: 0.38402778 | G15: 0.77569444 | H15: =IF(OR(F15="",G15=""),0,G15-F15-TIME(1,0,0)) -> 0.35 | I15: =IF(F15="","Absent",IF(F15>TIME(9,30,0),"Late","Present")) -> Present | J15: =IF(F15="","",IF(F15<=TIME(9,30,0),0,F15-TIME(9,30,0))) -> 0 | K15: =IF(AND(F15<>"",G15=""),"On Duty","")
A16: EMP105 | B16: Nithin V | C16: Mumbai | D16: Accounts | E16: Senior Accountant | F16: 0.38333333 | G16: 0.77847222 | H16: =IF(OR(F16="",G16=""),0,G16-F16-TIME(1,0,0)) -> 0.35347222 | I16: =IF(F16="","Absent",IF(F16>TIME(9,30,0),"Late","Present")) -> Present | J16: =IF(F16="","",IF(F16<=TIME(9,30,0),0,F16-TIME(9,30,0))) -> 0 | K16: =IF(AND(F16<>"",G16=""),"On Duty","")
A17: EMP118 | B17: Prakash Raj | C17: Delhi | D17: Accounts | E17: Senior Accountant | F17: 0.38680556 | G17: 0.78958333 | H17: =IF(OR(F17="",G17=""),0,G17-F17-TIME(1,0,0)) -> 0.36111111 | I17: =IF(F17="","Absent",IF(F17>TIME(9,30,0),"Late","Present")) -> Present | J17: =IF(F17="","",IF(F17<=TIME(9,30,0),0,F17-TIME(9,30,0))) -> 0 | K17: =IF(AND(F17<>"",G17=""),"On Duty","")
A18: EMP127 | B18: Dinesh Krishnan | C18: Hyderabad | D18: Accounts | E18: Accounts Manager | F18: 0.375 | G18: 0.77708333 | H18: =IF(OR(F18="",G18=""),0,G18-F18-TIME(1,0,0)) -> 0.36041667 | I18: =IF(F18="","Absent",IF(F18>TIME(9,30,0),"Late","Present")) -> Present | J18: =IF(F18="","",IF(F18<=TIME(9,30,0),0,F18-TIME(9,30,0))) -> 0 | K18: =IF(AND(F18<>"",G18=""),"On Duty","")
A19: EMP129 | B19: Dinesh Selvam | C19: Hyderabad | D19: Accounts | E19: Finance Executive | F19: 0.39305556 | G19: 0.78333333 | H19: =IF(OR(F19="",G19=""),0,G19-F19-TIME(1,0,0)) -> 0.34861111 | I19: =IF(F19="","Absent",IF(F19>TIME(9,30,0),"Late","Present")) -> Present | J19: =IF(F19="","",IF(F19<=TIME(9,30,0),0,F19-TIME(9,30,0))) -> 0 | K19: =IF(AND(F19<>"",G19=""),"On Duty","")
A20: EMP157 | B20: Yogesh S | C20: Coimbatore | D20: Accounts | E20: Accountant | F20: 0.39513889 | G20: 0.78194444 | H20: =IF(OR(F20="",G20=""),0,G20-F20-TIME(1,0,0)) -> 0.34513889 | I20: =IF(F20="","Absent",IF(F20>TIME(9,30,0),"Late","Present")) -> Present | J20: =IF(F20="","",IF(F20<=TIME(9,30,0),0,F20-TIME(9,30,0))) -> 0 | K20: =IF(AND(F20<>"",G20=""),"On Duty","")
A21: EMP158 | B21: Karthik P | C21: Ahmedabad | D21: Accounts | E21: Accounts Manager | F21: 0.4 | G21: 0.78333333 | H21: =IF(OR(F21="",G21=""),0,G21-F21-TIME(1,0,0)) -> 0.34166667 | I21: =IF(F21="","Absent",IF(F21>TIME(9,30,0),"Late","Present")) -> Late | J21: =IF(F21="","",IF(F21<=TIME(9,30,0),0,F21-TIME(9,30,0))) -> 0.0041666667 | K21: =IF(AND(F21<>"",G21=""),"On Duty","")
A22: EMP162 | B22: Ramesh G | C22: Chennai | D22: Accounts | E22: Accounts Executive | F22: 0.39722222 | H22: =IF(OR(F22="",G22=""),0,G22-F22-TIME(1,0,0)) -> 0 | I22: =IF(F22="","Absent",IF(F22>TIME(9,30,0),"Late","Present")) -> Late | J22: =IF(F22="","",IF(F22<=TIME(9,30,0),0,F22-TIME(9,30,0))) -> 0.0013888889 | K22: =IF(AND(F22<>"",G22=""),"On Duty","") -> On Duty
A23: EMP166 | B23: Dinesh B | C23: Pune | D23: Accounts | E23: Accounts Manager | F23: 0.39444444 | G23: 0.77361111 | H23: =IF(OR(F23="",G23=""),0,G23-F23-TIME(1,0,0)) -> 0.3375 | I23: =IF(F23="","Absent",IF(F23>TIME(9,30,0),"Late","Present")) -> Present | J23: =IF(F23="","",IF(F23<=TIME(9,30,0),0,F23-TIME(9,30,0))) -> 0 | K23: =IF(AND(F23<>"",G23=""),"On Duty","")
A24: EMP181 | B24: Manoj Narayanan | C24: Ahmedabad | D24: Accounts | E24: Senior Accountant | F24: 0.40138889 | G24: 0.7875 | H24: =IF(OR(F24="",G24=""),0,G24-F24-TIME(1,0,0)) -> 0.34444444 | I24: =IF(F24="","Absent",IF(F24>TIME(9,30,0),"Late","Present")) -> Late | J24: =IF(F24="","",IF(F24<=TIME(9,30,0),0,F24-TIME(9,30,0))) -> 0.0055555556 | K24: =IF(AND(F24<>"",G24=""),"On Duty","")
A25: EMP205 | B25: Manoj M | C25: Hyderabad | D25: Accounts | E25: Finance Executive | F25: 0.37916667 | G25: 0.77291667 | H25: =IF(OR(F25="",G25=""),0,G25-F25-TIME(1,0,0)) -> 0.35208333 | I25: =IF(F25="","Absent",IF(F25>TIME(9,30,0),"Late","Present")) -> Present | J25: =IF(F25="","",IF(F25<=TIME(9,30,0),0,F25-TIME(9,30,0))) -> 0 | K25: =IF(AND(F25<>"",G25=""),"On Duty","")
A26: EMP206 | B26: Naveen V | C26: Coimbatore | D26: Accounts | E26: Accounts Executive | F26: 0.39166667 | G26: 0.77152778 | H26: =IF(OR(F26="",G26=""),0,G26-F26-TIME(1,0,0)) -> 0.33819444 | I26: =IF(F26="","Absent",IF(F26>TIME(9,30,0),"Late","Present")) -> Present | J26: =IF(F26="","",IF(F26<=TIME(9,30,0),0,F26-TIME(9,30,0))) -> 0 | K26: =IF(AND(F26<>"",G26=""),"On Duty","")
A27: EMP208 | B27: Ganesh Krishnan | C27: Coimbatore | D27: Accounts | E27: Senior Accountant | F27: 0.38680556 | G27: 0.77430556 | H27: =IF(OR(F27="",G27=""),0,G27-F27-TIME(1,0,0)) -> 0.34583333 | I27: =IF(F27="","Absent",IF(F27>TIME(9,30,0),"Late","Present")) -> Present | J27: =IF(F27="","",IF(F27<=TIME(9,30,0),0,F27-TIME(9,30,0))) -> 0 | K27: =IF(AND(F27<>"",G27=""),"On Duty","")
A28: EMP218 | B28: Rahul V | C28: Noida | D28: Accounts | E28: Senior Accountant | F28: 0.40069444 | G28: 0.77986111 | H28: =IF(OR(F28="",G28=""),0,G28-F28-TIME(1,0,0)) -> 0.3375 | I28: =IF(F28="","Absent",IF(F28>TIME(9,30,0),"Late","Present")) -> Late | J28: =IF(F28="","",IF(F28<=TIME(9,30,0),0,F28-TIME(9,30,0))) -> 0.0048611111 | K28: =IF(AND(F28<>"",G28=""),"On Duty","")
A29: EMP229 | B29: Mohan Babu | C29: Noida | D29: Accounts | E29: Accountant | F29: 0.38541667 | G29: 0.775 | H29: =IF(OR(F29="",G29=""),0,G29-F29-TIME(1,0,0)) -> 0.34791667 | I29: =IF(F29="","Absent",IF(F29>TIME(9,30,0),"Late","Present")) -> Present | J29: =IF(F29="","",IF(F29<=TIME(9,30,0),0,F29-TIME(9,30,0))) -> 0 | K29: =IF(AND(F29<>"",G29=""),"On Duty","")
A30: EMP263 | B30: Bharath Prasad | C30: Delhi | D30: Accounts | E30: Accounts Executive | F30: 0.37916667 | G30: 0.78402778 | H30: =IF(OR(F30="",G30=""),0,G30-F30-TIME(1,0,0)) -> 0.36319444 | I30: =IF(F30="","Absent",IF(F30>TIME(9,30,0),"Late","Present")) -> Present | J30: =IF(F30="","",IF(F30<=TIME(9,30,0),0,F30-TIME(9,30,0))) -> 0 | K30: =IF(AND(F30<>"",G30=""),"On Duty","")
A31: EMP272 | B31: Bharath P | C31: Delhi | D31: Accounts | E31: Accountant | F31: 0.4 | H31: =IF(OR(F31="",G31=""),0,G31-F31-TIME(1,0,0)) -> 0 | I31: =IF(F31="","Absent",IF(F31>TIME(9,30,0),"Late","Present")) -> Late | J31: =IF(F31="","",IF(F31<=TIME(9,30,0),0,F31-TIME(9,30,0))) -> 0.0041666667 | K31: =IF(AND(F31<>"",G31=""),"On Duty","") -> On Duty
A32: EMP275 | B32: Ashwin Raja | C32: Kochi | D32: Accounts | E32: Accounts Executive | F32: 0.4 | G32: 0.77361111 | H32: =IF(OR(F32="",G32=""),0,G32-F32-TIME(1,0,0)) -> 0.33194444 | I32: =IF(F32="","Absent",IF(F32>TIME(9,30,0),"Late","Present")) -> Late | J32: =IF(F32="","",IF(F32<=TIME(9,30,0),0,F32-TIME(9,30,0))) -> 0.0041666667 | K32: =IF(AND(F32<>"",G32=""),"On Duty","")
A33: EMP291 | B33: Bharath N | C33: Chennai | D33: Accounts | E33: Senior Accountant | F33: 0.38125 | H33: =IF(OR(F33="",G33=""),0,G33-F33-TIME(1,0,0)) -> 0 | I33: =IF(F33="","Absent",IF(F33>TIME(9,30,0),"Late","Present")) -> Present | J33: =IF(F33="","",IF(F33<=TIME(9,30,0),0,F33-TIME(9,30,0))) -> 0 | K33: =IF(AND(F33<>"",G33=""),"On Duty","") -> On Duty
A34: EMP299 | B34: Ashwin B | C34: Ahmedabad | D34: Accounts | E34: Accountant | F34: 0.3875 | G34: 0.7875 | H34: =IF(OR(F34="",G34=""),0,G34-F34-TIME(1,0,0)) -> 0.35833333 | I34: =IF(F34="","Absent",IF(F34>TIME(9,30,0),"Late","Present")) -> Present | J34: =IF(F34="","",IF(F34<=TIME(9,30,0),0,F34-TIME(9,30,0))) -> 0 | K34: =IF(AND(F34<>"",G34=""),"On Duty","")
A35: EMP006 | B35: Karthik T | C35: Bengaluru | D35: Admin | E35: Admin Manager | F35: 0.38472222 | G35: 0.79097222 | H35: =IF(OR(F35="",G35=""),0,G35-F35-TIME(1,0,0)) -> 0.36458333 | I35: =IF(F35="","Absent",IF(F35>TIME(9,30,0),"Late","Present")) -> Present | J35: =IF(F35="","",IF(F35<=TIME(9,30,0),0,F35-TIME(9,30,0))) -> 0 | K35: =IF(AND(F35<>"",G35=""),"On Duty","")
A36: EMP007 | B36: Arun B | C36: Kochi | D36: Admin | E36: Office Coordinator | F36: 0.40208333 | G36: 0.77361111 | H36: =IF(OR(F36="",G36=""),0,G36-F36-TIME(1,0,0)) -> 0.32986111 | I36: =IF(F36="","Absent",IF(F36>TIME(9,30,0),"Late","Present")) -> Late | J36: =IF(F36="","",IF(F36<=TIME(9,30,0),0,F36-TIME(9,30,0))) -> 0.00625 | K36: =IF(AND(F36<>"",G36=""),"On Duty","")
A37: EMP012 | B37: Mohan M | C37: Chennai | D37: Admin | E37: Office Administrator | F37: 0.4 | G37: 0.77361111 | H37: =IF(OR(F37="",G37=""),0,G37-F37-TIME(1,0,0)) -> 0.33194444 | I37: =IF(F37="","Absent",IF(F37>TIME(9,30,0),"Late","Present")) -> Late | J37: =IF(F37="","",IF(F37<=TIME(9,30,0),0,F37-TIME(9,30,0))) -> 0.0041666667 | K37: =IF(AND(F37<>"",G37=""),"On Duty","")
A38: EMP015 | B38: Yogesh Babu | C38: Bengaluru | D38: Admin | E38: Office Administrator | F38: 0.39861111 | G38: 0.77430556 | H38: =IF(OR(F38="",G38=""),0,G38-F38-TIME(1,0,0)) -> 0.33402778 | I38: =IF(F38="","Absent",IF(F38>TIME(9,30,0),"Late","Present")) -> Late | J38: =IF(F38="","",IF(F38<=TIME(9,30,0),0,F38-TIME(9,30,0))) -> 0.0027777778 | K38: =IF(AND(F38<>"",G38=""),"On Duty","")
A39: EMP018 | B39: Naveen Prasad | C39: Pune | D39: Admin | E39: Admin Executive | F39: 0.3875 | G39: 0.77430556 | H39: =IF(OR(F39="",G39=""),0,G39-F39-TIME(1,0,0)) -> 0.34513889 | I39: =IF(F39="","Absent",IF(F39>TIME(9,30,0),"Late","Present")) -> Present | J39: =IF(F39="","",IF(F39<=TIME(9,30,0),0,F39-TIME(9,30,0))) -> 0 | K39: =IF(AND(F39<>"",G39=""),"On Duty","")
A40: EMP032 | B40: Nithin S | C40: Pune | D40: Admin | E40: Office Administrator | F40: 0.39166667 | H40: =IF(OR(F40="",G40=""),0,G40-F40-TIME(1,0,0)) -> 0 | I40: =IF(F40="","Absent",IF(F40>TIME(9,30,0),"Late","Present")) -> Present | J40: =IF(F40="","",IF(F40<=TIME(9,30,0),0,F40-TIME(9,30,0))) -> 0 | K40: =IF(AND(F40<>"",G40=""),"On Duty","") -> On Duty
A41: EMP035 | B41: Manoj Kumar | C41: Delhi | D41: Admin | E41: Admin Manager | F41: 0.39236111 | G41: 0.79097222 | H41: =IF(OR(F41="",G41=""),0,G41-F41-TIME(1,0,0)) -> 0.35694444 | I41: =IF(F41="","Absent",IF(F41>TIME(9,30,0),"Late","Present")) -> Present | J41: =IF(F41="","",IF(F41<=TIME(9,30,0),0,F41-TIME(9,30,0))) -> 0 | K41: =IF(AND(F41<>"",G41=""),"On Duty","")
A42: EMP074 | B42: Vinoth Raja | C42: Pune | D42: Admin | E42: Facility Executive | F42: 0.39791667 | H42: =IF(OR(F42="",G42=""),0,G42-F42-TIME(1,0,0)) -> 0 | I42: =IF(F42="","Absent",IF(F42>TIME(9,30,0),"Late","Present")) -> Late | J42: =IF(F42="","",IF(F42<=TIME(9,30,0),0,F42-TIME(9,30,0))) -> 0.0020833333 | K42: =IF(AND(F42<>"",G42=""),"On Duty","") -> On Duty
A43: EMP097 | B43: Sanjay Kannan | C43: Pune | D43: Admin | E43: Office Coordinator | F43: 0.39305556 | G43: 0.78541667 | H43: =IF(OR(F43="",G43=""),0,G43-F43-TIME(1,0,0)) -> 0.35069444 | I43: =IF(F43="","Absent",IF(F43>TIME(9,30,0),"Late","Present")) -> Present | J43: =IF(F43="","",IF(F43<=TIME(9,30,0),0,F43-TIME(9,30,0))) -> 0 | K43: =IF(AND(F43<>"",G43=""),"On Duty","")
A44: EMP108 | B44: Sanjay Raj | C44: Coimbatore | D44: Admin | E44: Office Coordinator | F44: 0.375 | G44: 0.775 | H44: =IF(OR(F44="",G44=""),0,G44-F44-TIME(1,0,0)) -> 0.35833333 | I44: =IF(F44="","Absent",IF(F44>TIME(9,30,0),"Late","Present")) -> Present | J44: =IF(F44="","",IF(F44<=TIME(9,30,0),0,F44-TIME(9,30,0))) -> 0 | K44: =IF(AND(F44<>"",G44=""),"On Duty","")
A45: EMP112 | B45: Prakash Selvam | C45: Hyderabad | D45: Admin | E45: Facility Executive | F45: 0.39652778 | G45: 0.77361111 | H45: =IF(OR(F45="",G45=""),0,G45-F45-TIME(1,0,0)) -> 0.33541667 | I45: =IF(F45="","Absent",IF(F45>TIME(9,30,0),"Late","Present")) -> Late | J45: =IF(F45="","",IF(F45<=TIME(9,30,0),0,F45-TIME(9,30,0))) -> 0.00069444444 | K45: =IF(AND(F45<>"",G45=""),"On Duty","")
A46: EMP149 | B46: Vinoth Narayanan | C46: Ahmedabad | D46: Admin | E46: Admin Executive | F46: 0.39652778 | G46: 0.775 | H46: =IF(OR(F46="",G46=""),0,G46-F46-TIME(1,0,0)) -> 0.33680556 | I46: =IF(F46="","Absent",IF(F46>TIME(9,30,0),"Late","Present")) -> Late | J46: =IF(F46="","",IF(F46<=TIME(9,30,0),0,F46-TIME(9,30,0))) -> 0.00069444444 | K46: =IF(AND(F46<>"",G46=""),"On Duty","")
A47: EMP173 | B47: Ajay Murugan | C47: Kochi | D47: Admin | E47: Facility Executive | H47: =IF(OR(F47="",G47=""),0,G47-F47-TIME(1,0,0)) -> 0 | I47: =IF(F47="","Absent",IF(F47>TIME(9,30,0),"Late","Present")) -> Absent | J47: =IF(F47="","",IF(F47<=TIME(9,30,0),0,F47-TIME(9,30,0))) | K47: =IF(AND(F47<>"",G47=""),"On Duty","")
A48: EMP178 | B48: Karthik Murugan | C48: Pune | D48: Admin | E48: Facility Executive | F48: 0.39583333 | G48: 0.78263889 | H48: =IF(OR(F48="",G48=""),0,G48-F48-TIME(1,0,0)) -> 0.34513889 | I48: =IF(F48="","Absent",IF(F48>TIME(9,30,0),"Late","Present")) -> Present | J48: =IF(F48="","",IF(F48<=TIME(9,30,0),0,F48-TIME(9,30,0))) -> 0 | K48: =IF(AND(F48<>"",G48=""),"On Duty","")
A49: EMP184 | B49: Ramesh R | C49: Pune | D49: Admin | E49: Admin Executive | F49: 0.38194444 | G49: 0.775 | H49: =IF(OR(F49="",G49=""),0,G49-F49-TIME(1,0,0)) -> 0.35138889 | I49: =IF(F49="","Absent",IF(F49>TIME(9,30,0),"Late","Present")) -> Present | J49: =IF(F49="","",IF(F49<=TIME(9,30,0),0,F49-TIME(9,30,0))) -> 0 | K49: =IF(AND(F49<>"",G49=""),"On Duty","")
A50: EMP190 | B50: Prakash Krishnan | C50: Mumbai | D50: Admin | E50: Office Administrator | F50: 0.38263889 | G50: 0.78263889 | H50: =IF(OR(F50="",G50=""),0,G50-F50-TIME(1,0,0)) -> 0.35833333 | I50: =IF(F50="","Absent",IF(F50>TIME(9,30,0),"Late","Present")) -> Present | J50: =IF(F50="","",IF(F50<=TIME(9,30,0),0,F50-TIME(9,30,0))) -> 0 | K50: =IF(AND(F50<>"",G50=""),"On Duty","")
A51: EMP191 | B51: Saravanan S | C51: Delhi | D51: Admin | E51: Office Administrator | F51: 0.40555556 | G51: 0.78958333 | H51: =IF(OR(F51="",G51=""),0,G51-F51-TIME(1,0,0)) -> 0.34236111 | I51: =IF(F51="","Absent",IF(F51>TIME(9,30,0),"Late","Present")) -> Late | J51: =IF(F51="","",IF(F51<=TIME(9,30,0),0,F51-TIME(9,30,0))) -> 0.0097222222 | K51: =IF(AND(F51<>"",G51=""),"On Duty","")
A52: EMP193 | B52: Suresh P | C52: Mumbai | D52: Admin | E52: Facility Executive | F52: 0.38125 | G52: 0.78194444 | H52: =IF(OR(F52="",G52=""),0,G52-F52-TIME(1,0,0)) -> 0.35902778 | I52: =IF(F52="","Absent",IF(F52>TIME(9,30,0),"Late","Present")) -> Present | J52: =IF(F52="","",IF(F52<=TIME(9,30,0),0,F52-TIME(9,30,0))) -> 0 | K52: =IF(AND(F52<>"",G52=""),"On Duty","")
A53: EMP243 | B53: Naveen Raja | C53: Ahmedabad | D53: Admin | E53: Admin Executive | F53: 0.39166667 | G53: 0.78888889 | H53: =IF(OR(F53="",G53=""),0,G53-F53-TIME(1,0,0)) -> 0.35555556 | I53: =IF(F53="","Absent",IF(F53>TIME(9,30,0),"Late","Present")) -> Present | J53: =IF(F53="","",IF(F53<=TIME(9,30,0),0,F53-TIME(9,30,0))) -> 0 | K53: =IF(AND(F53<>"",G53=""),"On Duty","")
A54: EMP245 | B54: Ajay P | C54: Mumbai | D54: Admin | E54: Office Administrator | F54: 0.39236111 | G54: 0.78055556 | H54: =IF(OR(F54="",G54=""),0,G54-F54-TIME(1,0,0)) -> 0.34652778 | I54: =IF(F54="","Absent",IF(F54>TIME(9,30,0),"Late","Present")) -> Present | J54: =IF(F54="","",IF(F54<=TIME(9,30,0),0,F54-TIME(9,30,0))) -> 0 | K54: =IF(AND(F54<>"",G54=""),"On Duty","")
A55: EMP259 | B55: Yuvaraj R | C55: Chennai | D55: Admin | E55: Office Coordinator | F55: 0.38263889 | G55: 0.78472222 | H55: =IF(OR(F55="",G55=""),0,G55-F55-TIME(1,0,0)) -> 0.36041667 | I55: =IF(F55="","Absent",IF(F55>TIME(9,30,0),"Late","Present")) -> Present | J55: =IF(F55="","",IF(F55<=TIME(9,30,0),0,F55-TIME(9,30,0))) -> 0 | K55: =IF(AND(F55<>"",G55=""),"On Duty","")
A56: EMP264 | B56: Deepak T | C56: Hyderabad | D56: Admin | E56: Facility Executive | F56: 0.39236111 | H56: =IF(OR(F56="",G56=""),0,G56-F56-TIME(1,0,0)) -> 0 | I56: =IF(F56="","Absent",IF(F56>TIME(9,30,0),"Late","Present")) -> Present | J56: =IF(F56="","",IF(F56<=TIME(9,30,0),0,F56-TIME(9,30,0))) -> 0 | K56: =IF(AND(F56<>"",G56=""),"On Duty","") -> On Duty
A57: EMP281 | B57: Praveen Kumar | C57: Kochi | D57: Admin | E57: Facility Executive | F57: 0.38194444 | H57: =IF(OR(F57="",G57=""),0,G57-F57-TIME(1,0,0)) -> 0 | I57: =IF(F57="","Absent",IF(F57>TIME(9,30,0),"Late","Present")) -> Present | J57: =IF(F57="","",IF(F57<=TIME(9,30,0),0,F57-TIME(9,30,0))) -> 0 | K57: =IF(AND(F57<>"",G57=""),"On Duty","") -> On Duty
A58: EMP286 | B58: Rahul N | C58: Coimbatore | D58: Admin | E58: Facility Executive | F58: 0.39861111 | H58: =IF(OR(F58="",G58=""),0,G58-F58-TIME(1,0,0)) -> 0 | I58: =IF(F58="","Absent",IF(F58>TIME(9,30,0),"Late","Present")) -> Late | J58: =IF(F58="","",IF(F58<=TIME(9,30,0),0,F58-TIME(9,30,0))) -> 0.0027777778 | K58: =IF(AND(F58<>"",G58=""),"On Duty","") -> On Duty
A59: EMP288 | B59: Ajay Kumar | C59: Coimbatore | D59: Admin | E59: Office Administrator | F59: 0.40138889 | G59: 0.77916667 | H59: =IF(OR(F59="",G59=""),0,G59-F59-TIME(1,0,0)) -> 0.33611111 | I59: =IF(F59="","Absent",IF(F59>TIME(9,30,0),"Late","Present")) -> Late | J59: =IF(F59="","",IF(F59<=TIME(9,30,0),0,F59-TIME(9,30,0))) -> 0.0055555556 | K59: =IF(AND(F59<>"",G59=""),"On Duty","")
A60: EMP298 | B60: Harish Narayanan | C60: Coimbatore | D60: Admin | E60: Admin Executive | F60: 0.39375 | G60: 0.78611111 | H60: =IF(OR(F60="",G60=""),0,G60-F60-TIME(1,0,0)) -> 0.35069444 | I60: =IF(F60="","Absent",IF(F60>TIME(9,30,0),"Late","Present")) -> Present | J60: =IF(F60="","",IF(F60<=TIME(9,30,0),0,F60-TIME(9,30,0))) -> 0 | K60: =IF(AND(F60<>"",G60=""),"On Duty","")
A61: EMP033 | B61: Karthik R | C61: Delhi | D61: Back End | E61: Data Entry Executive | F61: 0.39652778 | G61: 0.78402778 | H61: =IF(OR(F61="",G61=""),0,G61-F61-TIME(1,0,0)) -> 0.34583333 | I61: =IF(F61="","Absent",IF(F61>TIME(9,30,0),"Late","Present")) -> Late | J61: =IF(F61="","",IF(F61<=TIME(9,30,0),0,F61-TIME(9,30,0))) -> 0.00069444444 | K61: =IF(AND(F61<>"",G61=""),"On Duty","")
A62: EMP056 | B62: Yuvaraj P | C62: Noida | D62: Back End | E62: Operations Executive | F62: 0.37916667 | G62: 0.78472222 | H62: =IF(OR(F62="",G62=""),0,G62-F62-TIME(1,0,0)) -> 0.36388889 | I62: =IF(F62="","Absent",IF(F62>TIME(9,30,0),"Late","Present")) -> Present | J62: =IF(F62="","",IF(F62<=TIME(9,30,0),0,F62-TIME(9,30,0))) -> 0 | K62: =IF(AND(F62<>"",G62=""),"On Duty","")
A63: EMP062 | B63: Manoj Raj | C63: Mumbai | D63: Back End | E63: Documentation Executive | F63: 0.39583333 | G63: 0.77291667 | H63: =IF(OR(F63="",G63=""),0,G63-F63-TIME(1,0,0)) -> 0.33541667 | I63: =IF(F63="","Absent",IF(F63>TIME(9,30,0),"Late","Present")) -> Present | J63: =IF(F63="","",IF(F63<=TIME(9,30,0),0,F63-TIME(9,30,0))) -> 0 | K63: =IF(AND(F63<>"",G63=""),"On Duty","")
A64: EMP092 | B64: Karthik Babu | C64: Chennai | D64: Back End | E64: Data Entry Executive | F64: 0.38333333 | G64: 0.78472222 | H64: =IF(OR(F64="",G64=""),0,G64-F64-TIME(1,0,0)) -> 0.35972222 | I64: =IF(F64="","Absent",IF(F64>TIME(9,30,0),"Late","Present")) -> Present | J64: =IF(F64="","",IF(F64<=TIME(9,30,0),0,F64-TIME(9,30,0))) -> 0 | K64: =IF(AND(F64<>"",G64=""),"On Duty","")
A65: EMP114 | B65: Naveen Selvam | C65: Hyderabad | D65: Back End | E65: Operations Manager | F65: 0.4 | G65: 0.79027778 | H65: =IF(OR(F65="",G65=""),0,G65-F65-TIME(1,0,0)) -> 0.34861111 | I65: =IF(F65="","Absent",IF(F65>TIME(9,30,0),"Late","Present")) -> Late | J65: =IF(F65="","",IF(F65<=TIME(9,30,0),0,F65-TIME(9,30,0))) -> 0.0041666667 | K65: =IF(AND(F65<>"",G65=""),"On Duty","")
A66: EMP120 | B66: Vignesh Prasad | C66: Ahmedabad | D66: Back End | E66: Documentation Executive | F66: 0.37638889 | G66: 0.77361111 | H66: =IF(OR(F66="",G66=""),0,G66-F66-TIME(1,0,0)) -> 0.35555556 | I66: =IF(F66="","Absent",IF(F66>TIME(9,30,0),"Late","Present")) -> Present | J66: =IF(F66="","",IF(F66<=TIME(9,30,0),0,F66-TIME(9,30,0))) -> 0 | K66: =IF(AND(F66<>"",G66=""),"On Duty","")
A67: EMP124 | B67: Vinoth B | C67: Noida | D67: Back End | E67: Documentation Executive | F67: 0.38194444 | G67: 0.77638889 | H67: =IF(OR(F67="",G67=""),0,G67-F67-TIME(1,0,0)) -> 0.35277778 | I67: =IF(F67="","Absent",IF(F67>TIME(9,30,0),"Late","Present")) -> Present | J67: =IF(F67="","",IF(F67<=TIME(9,30,0),0,F67-TIME(9,30,0))) -> 0 | K67: =IF(AND(F67<>"",G67=""),"On Duty","")
A68: EMP137 | B68: Vignesh Kumar | C68: Ahmedabad | D68: Back End | E68: Operations Manager | F68: 0.37708333 | G68: 0.77847222 | H68: =IF(OR(F68="",G68=""),0,G68-F68-TIME(1,0,0)) -> 0.35972222 | I68: =IF(F68="","Absent",IF(F68>TIME(9,30,0),"Late","Present")) -> Present | J68: =IF(F68="","",IF(F68<=TIME(9,30,0),0,F68-TIME(9,30,0))) -> 0 | K68: =IF(AND(F68<>"",G68=""),"On Duty","")
A69: EMP144 | B69: Ramesh N | C69: Mumbai | D69: Back End | E69: Documentation Executive | F69: 0.38611111 | G69: 0.78333333 | H69: =IF(OR(F69="",G69=""),0,G69-F69-TIME(1,0,0)) -> 0.35555556 | I69: =IF(F69="","Absent",IF(F69>TIME(9,30,0),"Late","Present")) -> Present | J69: =IF(F69="","",IF(F69<=TIME(9,30,0),0,F69-TIME(9,30,0))) -> 0 | K69: =IF(AND(F69<>"",G69=""),"On Duty","")
A70: EMP146 | B70: Dinesh Kannan | C70: Hyderabad | D70: Back End | E70: Documentation Executive | F70: 0.39861111 | G70: 0.78055556 | H70: =IF(OR(F70="",G70=""),0,G70-F70-TIME(1,0,0)) -> 0.34027778 | I70: =IF(F70="","Absent",IF(F70>TIME(9,30,0),"Late","Present")) -> Late | J70: =IF(F70="","",IF(F70<=TIME(9,30,0),0,F70-TIME(9,30,0))) -> 0.0027777778 | K70: =IF(AND(F70<>"",G70=""),"On Duty","")
... A73: EMP198 | B73: Ajay Narayanan | C73: Delhi | D73: Back End | E73: Documentation Executive | F73: 0.40069444 | G73: 0.77361111 | H73: =IF(OR(F73="",G73=""),0,G73-F73-TIME(1,0,0)) -> 0.33125 | I73: =IF(F73="","Absent",IF(F73>TIME(9,30,0),"Late","Present")) -> Late | J73: =IF(F73="","",IF(F73<=TIME(9,30,0),0,F73-TIME(9,30,0))) -> 0.0048611111 | K73: =IF(AND(F73<>"",G73=""),"On Duty","")
A74: EMP200 | B74: Vijay B | C74: Ahmedabad | D74: Back End | E74: Operations Manager | F74: 0.38263889 | H74: =IF(OR(F74="",G74=""),0,G74-F74-TIME(1,0,0)) -> 0 | I74: =IF(F74="","Absent",IF(F74>TIME(9,30,0),"Late","Present")) -> Present | J74: =IF(F74="","",IF(F74<=TIME(9,30,0),0,F74-TIME(9,30,0))) -> 0 | K74: =IF(AND(F74<>"",G74=""),"On Duty","") -> On Duty
A75: EMP202 | B75: Mohan B | C75: Hyderabad | D75: Back End | E75: Data Entry Executive | F75: 0.40347222 | G75: 0.78611111 | H75: =IF(OR(F75="",G75=""),0,G75-F75-TIME(1,0,0)) -> 0.34097222 | I75: =IF(F75="","Absent",IF(F75>TIME(9,30,0),"Late","Present")) -> Late | J75: =IF(F75="","",IF(F75<=TIME(9,30,0),0,F75-TIME(9,30,0))) -> 0.0076388889 | K75: =IF(AND(F75<>"",G75=""),"On Duty","")
A76: EMP203 | B76: Dinesh G | C76: Coimbatore | D76: Back End | E76: Operations Executive | F76: 0.37847222 | G76: 0.78958333 | H76: =IF(OR(F76="",G76=""),0,G76-F76-TIME(1,0,0)) -> 0.36944444 | I76: =IF(F76="","Absent",IF(F76>TIME(9,30,0),"Late","Present")) -> Present | J76: =IF(F76="","",IF(F76<=TIME(9,30,0),0,F76-TIME(9,30,0))) -> 0 | K76: =IF(AND(F76<>"",G76=""),"On Duty","")
A77: EMP204 | B77: Yogesh Narayanan | C77: Pune | D77: Back End | E77: Operations Manager | F77: 0.38263889 | G77: 0.78333333 | H77: =IF(OR(F77="",G77=""),0,G77-F77-TIME(1,0,0)) -> 0.35902778 | I77: =IF(F77="","Absent",IF(F77>TIME(9,30,0),"Late","Present")) -> Present | J77: =IF(F77="","",IF(F77<=TIME(9,30,0),0,F77-TIME(9,30,0))) -> 0 | K77: =IF(AND(F77<>"",G77=""),"On Duty","")
A78: EMP213 | B78: Saravanan Narayanan | C78: Hyderabad | D78: Back End | E78: Operations Executive | F78: 0.38333333 | G78: 0.78611111 | H78: =IF(OR(F78="",G78=""),0,G78-F78-TIME(1,0,0)) -> 0.36111111 | I78: =IF(F78="","Absent",IF(F78>TIME(9,30,0),"Late","Present")) -> Present | J78: =IF(F78="","",IF(F78<=TIME(9,30,0),0,F78-TIME(9,30,0))) -> 0 | K78: =IF(AND(F78<>"",G78=""),"On Duty","")
A79: EMP221 | B79: Lokesh K | C79: Chennai | D79: Back End | E79: Documentation Executive | F79: 0.38125 | G79: 0.7875 | H79: =IF(OR(F79="",G79=""),0,G79-F79-TIME(1,0,0)) -> 0.36458333 | I79: =IF(F79="","Absent",IF(F79>TIME(9,30,0),"Late","Present")) -> Present | J79: =IF(F79="","",IF(F79<=TIME(9,30,0),0,F79-TIME(9,30,0))) -> 0 | K79: =IF(AND(F79<>"",G79=""),"On Duty","")
A80: EMP227 | B80: Mohan N | C80: Hyderabad | D80: Back End | E80: MIS Executive | F80: 0.37708333 | G80: 0.79097222 | H80: =IF(OR(F80="",G80=""),0,G80-F80-TIME(1,0,0)) -> 0.37222222 | I80: =IF(F80="","Absent",IF(F80>TIME(9,30,0),"Late","Present")) -> Present | J80: =IF(F80="","",IF(F80<=TIME(9,30,0),0,F80-TIME(9,30,0))) -> 0 | K80: =IF(AND(F80<>"",G80=""),"On Duty","")
A81: EMP234 | B81: Lokesh Selvam | C81: Bengaluru | D81: Back End | E81: MIS Executive | F81: 0.39236111 | G81: 0.79097222 | H81: =IF(OR(F81="",G81=""),0,G81-F81-TIME(1,0,0)) -> 0.35694444 | I81: =IF(F81="","Absent",IF(F81>TIME(9,30,0),"Late","Present")) -> Present | J81: =IF(F81="","",IF(F81<=TIME(9,30,0),0,F81-TIME(9,30,0))) -> 0 | K81: =IF(AND(F81<>"",G81=""),"On Duty","")
A82: EMP277 | B82: Sanjay R | C82: Noida | D82: Back End | E82: Operations Executive | F82: 0.39444444 | G82: 0.78402778 | H82: =IF(OR(F82="",G82=""),0,G82-F82-TIME(1,0,0)) -> 0.34791667 | I82: =IF(F82="","Absent",IF(F82>TIME(9,30,0),"Late","Present")) -> Present | J82: =IF(F82="","",IF(F82<=TIME(9,30,0),0,F82-TIME(9,30,0))) -> 0 | K82: =IF(AND(F82<>"",G82=""),"On Duty","")
A83: EMP003 | B83: Aravind B | C83: Chennai | D83: Business Development | E83: Senior Business Development Executive | F83: 0.40555556 | H83: =IF(OR(F83="",G83=""),0,G83-F83-TIME(1,0,0)) -> 0 | I83: =IF(F83="","Absent",IF(F83>TIME(9,30,0),"Late","Present")) -> Late | J83: =IF(F83="","",IF(F83<=TIME(9,30,0),0,F83-TIME(9,30,0))) -> 0.0097222222 | K83: =IF(AND(F83<>"",G83=""),"On Duty","") -> On Duty
A84: EMP017 | B84: Vignesh Kannan | C84: Kochi | D84: Business Development | E84: Corporate Sales Executive | F84: 0.40347222 | G84: 0.77222222 | H84: =IF(OR(F84="",G84=""),0,G84-F84-TIME(1,0,0)) -> 0.32708333 | I84: =IF(F84="","Absent",IF(F84>TIME(9,30,0),"Late","Present")) -> Late | J84: =IF(F84="","",IF(F84<=TIME(9,30,0),0,F84-TIME(9,30,0))) -> 0.0076388889 | K84: =IF(AND(F84<>"",G84=""),"On Duty","")
A85: EMP021 | B85: Arun Raj | C85: Bengaluru | D85: Business Development | E85: Growth Executive | F85: 0.40138889 | G85: 0.79097222 | H85: =IF(OR(F85="",G85=""),0,G85-F85-TIME(1,0,0)) -> 0.34791667 | I85: =IF(F85="","Absent",IF(F85>TIME(9,30,0),"Late","Present")) -> Late | J85: =IF(F85="","",IF(F85<=TIME(9,30,0),0,F85-TIME(9,30,0))) -> 0.0055555556 | K85: =IF(AND(F85<>"",G85=""),"On Duty","")
A86: EMP022 | B86: Madhan Raj | C86: Mumbai | D86: Business Development | E86: Growth Executive | F86: 0.38888889 | G86: 0.77361111 | H86: =IF(OR(F86="",G86=""),0,G86-F86-TIME(1,0,0)) -> 0.34305556 | I86: =IF(F86="","Absent",IF(F86>TIME(9,30,0),"Late","Present")) -> Present | J86: =IF(F86="","",IF(F86<=TIME(9,30,0),0,F86-TIME(9,30,0))) -> 0 | K86: =IF(AND(F86<>"",G86=""),"On Duty","")
A87: EMP024 | B87: Harish Raja | C87: Ahmedabad | D87: Business Development | E87: Growth Executive | F87: 0.40486111 | G87: 0.78402778 | H87: =IF(OR(F87="",G87=""),0,G87-F87-TIME(1,0,0)) -> 0.3375 | I87: =IF(F87="","Absent",IF(F87>TIME(9,30,0),"Late","Present")) -> Late | J87: =IF(F87="","",IF(F87<=TIME(9,30,0),0,F87-TIME(9,30,0))) -> 0.0090277778 | K87: =IF(AND(F87<>"",G87=""),"On Duty","")
A88: EMP036 | B88: Madhan Narayanan | C88: Bengaluru | D88: Business Development | E88: Corporate Sales Executive | F88: 0.37847222 | H88: =IF(OR(F88="",G88=""),0,G88-F88-TIME(1,0,0)) -> 0 | I88: =IF(F88="","Absent",IF(F88>TIME(9,30,0),"Late","Present")) -> Present | J88: =IF(F88="","",IF(F88<=TIME(9,30,0),0,F88-TIME(9,30,0))) -> 0 | K88: =IF(AND(F88<>"",G88=""),"On Duty","") -> On Duty
A89: EMP073 | B89: Sanjay Kumar | C89: Bengaluru | D89: Business Development | E89: Senior Business Development Executive | F89: 0.39236111 | G89: 0.78888889 | H89: =IF(OR(F89="",G89=""),0,G89-F89-TIME(1,0,0)) -> 0.35486111 | I89: =IF(F89="","Absent",IF(F89>TIME(9,30,0),"Late","Present")) -> Present | J89: =IF(F89="","",IF(F89<=TIME(9,30,0),0,F89-TIME(9,30,0))) -> 0 | K89: =IF(AND(F89<>"",G89=""),"On Duty","")
A90: EMP078 | B90: Harish Babu | C90: Noida | D90: Business Development | E90: Growth Executive | F90: 0.38125 | G90: 0.77222222 | H90: =IF(OR(F90="",G90=""),0,G90-F90-TIME(1,0,0)) -> 0.34930556 | I90: =IF(F90="","Absent",IF(F90>TIME(9,30,0),"Late","Present")) -> Present | J90: =IF(F90="","",IF(F90<=TIME(9,30,0),0,F90-TIME(9,30,0))) -> 0 | K90: =IF(AND(F90<>"",G90=""),"On Duty","")
A91: EMP080 | B91: Aravind N | C91: Mumbai | D91: Business Development | E91: Business Development Manager | F91: 0.38125 | G91: 0.78680556 | H91: =IF(OR(F91="",G91=""),0,G91-F91-TIME(1,0,0)) -> 0.36388889 | I91: =IF(F91="","Absent",IF(F91>TIME(9,30,0),"Late","Present")) -> Present | J91: =IF(F91="","",IF(F91<=TIME(9,30,0),0,F91-TIME(9,30,0))) -> 0 | K91: =IF(AND(F91<>"",G91=""),"On Duty","")
A92: EMP084 | B92: Arun Raja | C92: Coimbatore | D92: Business Development | E92: Senior Business Development Executive | F92: 0.38402778 | G92: 0.77361111 | H92: =IF(OR(F92="",G92=""),0,G92-F92-TIME(1,0,0)) -> 0.34791667 | I92: =IF(F92="","Absent",IF(F92>TIME(9,30,0),"Late","Present")) -> Present | J92: =IF(F92="","",IF(F92<=TIME(9,30,0),0,F92-TIME(9,30,0))) -> 0 | K92: =IF(AND(F92<>"",G92=""),"On Duty","")
A93: EMP100 | B93: Deepak K | C93: Bengaluru | D93: Business Development | E93: Growth Executive | F93: 0.38055556 | G93: 0.77986111 | H93: =IF(OR(F93="",G93=""),0,G93-F93-TIME(1,0,0)) -> 0.35763889 | I93: =IF(F93="","Absent",IF(F93>TIME(9,30,0),"Late","Present")) -> Present | J93: =IF(F93="","",IF(F93<=TIME(9,30,0),0,F93-TIME(9,30,0))) -> 0 | K93: =IF(AND(F93<>"",G93=""),"On Duty","")
A94: EMP101 | B94: Rahul Babu | C94: Noida | D94: Business Development | E94: Growth Executive | F94: 0.39861111 | G94: 0.78125 | H94: =IF(OR(F94="",G94=""),0,G94-F94-TIME(1,0,0)) -> 0.34097222 | I94: =IF(F94="","Absent",IF(F94>TIME(9,30,0),"Late","Present")) -> Late | J94: =IF(F94="","",IF(F94<=TIME(9,30,0),0,F94-TIME(9,30,0))) -> 0.0027777778 | K94: =IF(AND(F94<>"",G94=""),"On Duty","")
A95: EMP117 | B95: Kishore S | C95: Ahmedabad | D95: Business Development | E95: Senior Business Development Executive | F95: 0.40555556 | G95: 0.78194444 | H95: =IF(OR(F95="",G95=""),0,G95-F95-TIME(1,0,0)) -> 0.33472222 | I95: =IF(F95="","Absent",IF(F95>TIME(9,30,0),"Late","Present")) -> Late | J95: =IF(F95="","",IF(F95<=TIME(9,30,0),0,F95-TIME(9,30,0))) -> 0.0097222222 | K95: =IF(AND(F95<>"",G95=""),"On Duty","")
A96: EMP132 | B96: Ganesh Raj | C96: Ahmedabad | D96: Business Development | E96: Business Development Manager | F96: 0.4 | G96: 0.78402778 | H96: =IF(OR(F96="",G96=""),0,G96-F96-TIME(1,0,0)) -> 0.34236111 | I96: =IF(F96="","Absent",IF(F96>TIME(9,30,0),"Late","Present")) -> Late | J96: =IF(F96="","",IF(F96<=TIME(9,30,0),0,F96-TIME(9,30,0))) -> 0.0041666667 | K96: =IF(AND(F96<>"",G96=""),"On Duty","")
A97: EMP136 | B97: Ashwin Raj | C97: Hyderabad | D97: Business Development | E97: Business Development Manager | F97: 0.40625 | G97: 0.77083333 | H97: =IF(OR(F97="",G97=""),0,G97-F97-TIME(1,0,0)) -> 0.32291667 | I97: =IF(F97="","Absent",IF(F97>TIME(9,30,0),"Late","Present")) -> Late | J97: =IF(F97="","",IF(F97<=TIME(9,30,0),0,F97-TIME(9,30,0))) -> 0.010416667 | K97: =IF(AND(F97<>"",G97=""),"On Duty","")
A98: EMP140 | B98: Sathish S | C98: Noida | D98: Business Development | E98: Corporate Sales Executive | F98: 0.38263889 | G98: 0.78541667 | H98: =IF(OR(F98="",G98=""),0,G98-F98-TIME(1,0,0)) -> 0.36111111 | I98: =IF(F98="","Absent",IF(F98>TIME(9,30,0),"Late","Present")) -> Present | J98: =IF(F98="","",IF(F98<=TIME(9,30,0),0,F98-TIME(9,30,0))) -> 0 | K98: =IF(AND(F98<>"",G98=""),"On Duty","")
A99: EMP143 | B99: Mohan G | C99: Pune | D99: Business Development | E99: Corporate Sales Executive | F99: 0.39166667 | G99: 0.78402778 | H99: =IF(OR(F99="",G99=""),0,G99-F99-TIME(1,0,0)) -> 0.35069444 | I99: =IF(F99="","Absent",IF(F99>TIME(9,30,0),"Late","Present")) -> Present | J99: =IF(F99="","",IF(F99<=TIME(9,30,0),0,F99-TIME(9,30,0))) -> 0 | K99: =IF(AND(F99<>"",G99=""),"On Duty","")
A100: EMP167 | B100: Kishore Krishnan | C100: Coimbatore | D100: Business Development | E100: Senior Business Development Executive | F100: 0.37777778 | G100: 0.78472222 | H100: =IF(OR(F100="",G100=""),0,G100-F100-TIME(1,0,0)) -> 0.36527778 | I100: =IF(F100="","Absent",IF(F100>TIME(9,30,0),"Late","Present")) -> Present | J100: =IF(F100="","",IF(F100<=TIME(9,30,0),0,F100-TIME(9,30,0))) -> 0 | K100: =IF(AND(F100<>"",G100=""),"On Duty","")
... A107: EMP274 | B107: Saravanan Babu | C107: Chennai | D107: Business Development | E107: Business Development Executive | F107: 0.39444444 | G107: 0.78888889 | H107: =IF(OR(F107="",G107=""),0,G107-F107-TIME(1,0,0)) -> 0.35277778 | I107: =IF(F107="","Absent",IF(F107>TIME(9,30,0),"Late","Present")) -> Present | J107: =IF(F107="","",IF(F107<=TIME(9,30,0),0,F107-TIME(9,30,0))) -> 0 | K107: =IF(AND(F107<>"",G107=""),"On Duty","")
A108: EMP031 | B108: Aravind M | C108: Coimbatore | D108: Customer Relationship | E108: Customer Service Executive | F108: 0.38958333 | H108: =IF(OR(F108="",G108=""),0,G108-F108-TIME(1,0,0)) -> 0 | I108: =IF(F108="","Absent",IF(F108>TIME(9,30,0),"Late","Present")) -> Present | J108: =IF(F108="","",IF(F108<=TIME(9,30,0),0,F108-TIME(9,30,0))) -> 0 | K108: =IF(AND(F108<>"",G108=""),"On Duty","") -> On Duty
...

Sheet MONTHLY ATTENDANCE SUMMARY
A1: MONTHLY ATTENDANCE SUMMARY
A2: Employee Number | B2: Name | C2: Department | D2: Present | E2: Absent | F2: Leave | G2: Week Off | H2: Work Hours | I2: Attendance Percentage
A3: {=_xlfn.SORTBY('EMPLOYEE MASTER DATA'!A4:B303,'EMPLOYEE MASTER DATA'!A4:A303,1)} -> EMP001 | B3: Vijay V | C3: =_xlfn.XLOOKUP('MONTHLY ATTENDANCE SUMMARY'!A3,'EMPLOYEE MASTER DATA'!A4:A303,'EMPLOYEE MASTER DATA'!D4:D303) -> Production | D3: 18 | E3: =MAX(0,24-(D3+F3)) -> 4 | F3: 2 | G3: 4 | H3: =D3*TIME(8,30,0) -> 6.375 | I3: =IF(D3+E3+F3=0,0,D3/(D3+E3+F3)) -> 0.75
A4: EMP002 | B4: Sathish V | C4: =_xlfn.XLOOKUP('MONTHLY ATTENDANCE SUMMARY'!A4,'EMPLOYEE MASTER DATA'!A5:A304,'EMPLOYEE MASTER DATA'!D5:D304) -> Production | D4: 20 | E4: =MAX(0,24-(D4+F4)) -> 2 | F4: 2 | G4: 4 | H4: =D4*TIME(8,30,0) -> 7.0833333 | I4: =IF(D4+E4+F4=0,0,D4/(D4+E4+F4)) -> 0.83333333
A5: EMP003 | B5: Aravind B | C5: =_xlfn.XLOOKUP('MONTHLY ATTENDANCE SUMMARY'!A5,'EMPLOYEE MASTER DATA'!A6:A305,'EMPLOYEE MASTER DATA'!D6:D305) -> Business Development | D5: 22 | E5: =MAX(0,24-(D5+F5)) -> 1 | F5: 1 | G5: 4 | H5: =D5*TIME(8,30,0) -> 7.7916667 | I5: =IF(D5+E5+F5=0,0,D5/(D5+E5+F5)) -> 0.91666667
A6: EMP004 | B6: Ramesh Kumar | C6: =_xlfn.XLOOKUP('MONTHLY ATTENDANCE SUMMARY'!A6,'EMPLOYEE MASTER DATA'!A7:A306,'EMPLOYEE MASTER DATA'!D7:D306) -> Front Office | D6: 22 | E6: =MAX(0,24-(D6+F6)) -> 1 | F6: 1 | G6: 4 | H6: =D6*TIME(8,30,0) -> 7.7916667 | I6: =IF(D6+E6+F6=0,0,D6/(D6+E6+F6)) -> 0.91666667
A7: EMP005 | B7: Naveen Kumar | C7: =_xlfn.XLOOKUP('MONTHLY ATTENDANCE SUMMARY'!A7,'EMPLOYEE MASTER DATA'!A8:A307,'EMPLOYEE MASTER DATA'!D8:D307) -> Front Office | D7: 18 | E7: =MAX(0,24-(D7+F7)) -> 5 | F7: 1 | G7: 4 | H7: =D7*TIME(8,30,0) -> 6.375 | I7: =IF(D7+E7+F7=0,0,D7/(D7+E7+F7)) -> 0.75
A8: EMP006 | B8: Karthik T | C8: =_xlfn.XLOOKUP('MONTHLY ATTENDANCE SUMMARY'!A8,'EMPLOYEE MASTER DATA'!A9:A308,'EMPLOYEE MASTER DATA'!D9:D308) -> Admin | D8: 18 | E8: =MAX(0,24-(D8+F8)) -> 4 | F8: 2 | G8: 4 | H8: =D8*TIME(8,30,0) -> 6.375 | I8: =IF(D8+E8+F8=0,0,D8/(D8+E8+F8)) -> 0.75
A9: EMP007 | B9: Arun B | C9: =_xlfn.XLOOKUP('MONTHLY ATTENDANCE SUMMARY'!A9,'EMPLOYEE MASTER DATA'!A10:A309,'EMPLOYEE MASTER DATA'!D10:D309) -> Admin | D9: 13 | E9: =MAX(0,24-(D9+F9)) -> 10 | F9: 1 | G9: 4 | H9: =D9*TIME(8,30,0) -> 4.6041667 | I9: =IF(D9+E9+F9=0,0,D9/(D9+E9+F9)) -> 0.54166667
A10: EMP008 | B10: Sathish G | C10: =_xlfn.XLOOKUP('MONTHLY ATTENDANCE SUMMARY'!A10,'EMPLOYEE MASTER DATA'!A11:A310,'EMPLOYEE MASTER DATA'!D11:D310) -> Accounts | D10: 18 | E10: =MAX(0,24-(D10+F10)) -> 4 | F10: 2 | G10: 4 | H10: =D10*TIME(8,30,0) -> 6.375 | I10: =IF(D10+E10+F10=0,0,D10/(D10+E10+F10)) -> 0.75
A11: EMP009 | B11: Yuvaraj Babu | C11: =_xlfn.XLOOKUP('MONTHLY ATTENDANCE SUMMARY'!A11,'EMPLOYEE MASTER DATA'!A12:A311,'EMPLOYEE MASTER DATA'!D12:D311) -> Sales | D11: 22 | E11: =MAX(0,24-(D11+F11)) -> 1 | F11: 1 | G11: 4 | H11: =D11*TIME(8,30,0) -> 7.7916667 | I11: =IF(D11+E11+F11=0,0,D11/(D11+E11+F11)) -> 0.91666667
A12: EMP010 | B12: Sanjay G | C12: =_xlfn.XLOOKUP('MONTHLY ATTENDANCE SUMMARY'!A12,'EMPLOYEE MASTER DATA'!A13:A312,'EMPLOYEE MASTER DATA'!D13:D312) -> Procurement | D12: 22 | E12: =MAX(0,24-(D12+F12)) -> 1 | F12: 1 | G12: 4 | H12: =D12*TIME(8,30,0) -> 7.7916667 | I12: =IF(D12+E12+F12=0,0,D12/(D12+E12+F12)) -> 0.91666667
A13: EMP011 | B13: Vijay T | C13: =_xlfn.XLOOKUP('MONTHLY ATTENDANCE SUMMARY'!A13,'EMPLOYEE MASTER DATA'!A14:A313,'EMPLOYEE MASTER DATA'!D14:D313) -> Accounts | D13: 21 | E13: =MAX(0,24-(D13+F13)) -> 2 | F13: 1 | G13: 4 | H13: =D13*TIME(8,30,0) -> 7.4375 | I13: =IF(D13+E13+F13=0,0,D13/(D13+E13+F13)) -> 0.875
A14: EMP012 | B14: Mohan M | C14: =_xlfn.XLOOKUP('MONTHLY ATTENDANCE SUMMARY'!A14,'EMPLOYEE MASTER DATA'!A15:A314,'EMPLOYEE MASTER DATA'!D15:D314) -> Admin | D14: 19 | E14: =MAX(0,24-(D14+F14)) -> 4 | F14: 1 | G14: 4 | H14: =D14*TIME(8,30,0) -> 6.7291667 | I14: =IF(D14+E14+F14=0,0,D14/(D14+E14+F14)) -> 0.79166667
A15: EMP013 | B15: Madhan Selvam | C15: =_xlfn.XLOOKUP('MONTHLY ATTENDANCE SUMMARY'!A15,'EMPLOYEE MASTER DATA'!A16:A315,'EMPLOYEE MASTER DATA'!D16:D315) -> Accounts | D15: 21 | E15: =MAX(0,24-(D15+F15)) -> 1 | F15: 2 | G15: 4 | H15: =D15*TIME(8,30,0) -> 7.4375 | I15: =IF(D15+E15+F15=0,0,D15/(D15+E15+F15)) -> 0.875
... A302: EMP300 | B302: Ganesh Narayanan | C302: =_xlfn.XLOOKUP('MONTHLY ATTENDANCE SUMMARY'!A302,'EMPLOYEE MASTER DATA'!A303:A602,'EMPLOYEE MASTER DATA'!D303:D602) -> Maintenance | D302: 15 | E302: =MAX(0,24-(D302+F302)) -> 7 | F302: 2 | G302: 4 | H302: =D302*TIME(8,30,0) -> 5.3125 | I302: =IF(D302+E302+F302=0,0,D302/(D302+E302+F302)) -> 0.625

Sheet PAYROLL
A1: PAYROLL
A2: Employee Details | E2: Salary Details | G2: Attendance | K2: Deductions
A3: Employee No. | B3: Name | C3: Department | D3: Designation | E3: Basic Salary | F3: Per Day Salary | G3: Present Days | H3: Approved Leaves | I3: Full Pay | J3: Half Pay | K3: Gross Salary | L3: PF | M3: Professional Tax | N3: ESI | O3: NetSalary
A4: {=_xlfn.SORTBY('EMPLOYEE MASTER DATA'!A4:B303,'EMPLOYEE MASTER DATA'!A4:A303,1)} -> EMP001 | B4: Vijay V | C4: =_xlfn.XLOOKUP(A4,'EMPLOYEE MASTER DATA'!A4:A303,'EMPLOYEE MASTER DATA'!D4:D303) -> Production | D4: =_xlfn.XLOOKUP(A4,'EMPLOYEE MASTER DATA'!A4:A303,'EMPLOYEE MASTER DATA'!E4:E303) -> Production Executive | E4: =_xlfn.XLOOKUP(A4,'EMPLOYEE MASTER DATA'!A4:A303,'EMPLOYEE MASTER DATA'!F4:F303) -> 29000 | F4: =E4/24 -> 1208.3333 | G4: {=_xlfn.XLOOKUP(PAYROLL!A4:A303,'MONTHLY ATTENDANCE SUMMARY'!A3:A302,'MONTHLY ATTENDANCE SUMMARY'!D3:D302)} -> 18 | H4: =_xlfn.XLOOKUP(A4,'MONTHLY ATTENDANCE SUMMARY'!A3:A302,'MONTHLY ATTENDANCE SUMMARY'!F3:F302) -> 2 | I4: =MIN(H4,1) -> 1 | J4: =MAX(H4-1,0) -> 1 | K4: =F4*(G4+I4+(J4*0.5)) -> 23562.5 | L4: =E4*12% -> 3480 | M4: =IF(K4>=21000,200,0) -> 200 | N4: =IF(K4<=21000,K4*0.75%,0) -> 0 | O4: =K4-SUM(L4:N4) -> 19882.5
A5: EMP002 | B5: Sathish V | C5: =_xlfn.XLOOKUP(A5,'EMPLOYEE MASTER DATA'!A5:A304,'EMPLOYEE MASTER DATA'!D5:D304) -> Production | D5: =_xlfn.XLOOKUP(A5,'EMPLOYEE MASTER DATA'!A5:A304,'EMPLOYEE MASTER DATA'!E5:E304) -> Shift Incharge | E5: =_xlfn.XLOOKUP(A5,'EMPLOYEE MASTER DATA'!A5:A304,'EMPLOYEE MASTER DATA'!F5:F304) -> 46500 | F5: =E5/24 -> 1937.5 | G5: 20 | H5: =_xlfn.XLOOKUP(A5,'MONTHLY ATTENDANCE SUMMARY'!A4:A303,'MONTHLY ATTENDANCE SUMMARY'!F4:F303) -> 2 | I5: =MIN(H5,1) -> 1 | J5: =MAX(H5-1,0) -> 1 | K5: =F5*(G5+I5+(J5*0.5)) -> 41656.25 | L5: =E5*12% -> 5580 | M5: =IF(K5>=21000,200,0) -> 200 | N5: =IF(K5<=21000,K5*0.75%,0) -> 0 | O5: =K5-SUM(L5:N5) -> 35876.25
A6: EMP003 | B6: Aravind B | C6: =_xlfn.XLOOKUP(A6,'EMPLOYEE MASTER DATA'!A6:A305,'EMPLOYEE MASTER DATA'!D6:D305) -> Business Development | D6: =_xlfn.XLOOKUP(A6,'EMPLOYEE MASTER DATA'!A6:A305,'EMPLOYEE MASTER DATA'!E6:E305) -> Senior Business Development Executive | E6: =_xlfn.XLOOKUP(A6,'EMPLOYEE MASTER DATA'!A6:A305,'EMPLOYEE MASTER DATA'!F6:F305) -> 44500 | F6: =E6/24 -> 1854.1667 | G6: 22 | H6: =_xlfn.XLOOKUP(A6,'MONTHLY ATTENDANCE SUMMARY'!A5:A304,'MONTHLY ATTENDANCE SUMMARY'!F5:F304) -> 1 | I6: =MIN(H6,1) -> 1 | J6: =MAX(H6-1,0) -> 0 | K6: =F6*(G6+I6+(J6*0.5)) -> 42645.833 | L6: =E6*12% -> 5340 | M6: =IF(K6>=21000,200,0) -> 200 | N6: =IF(K6<=21000,K6*0.75%,0) -> 0 | O6: =K6-SUM(L6:N6) -> 37105.833
A7: EMP004 | B7: Ramesh Kumar | C7: =_xlfn.XLOOKUP(A7,'EMPLOYEE MASTER DATA'!A7:A306,'EMPLOYEE MASTER DATA'!D7:D306) -> Front Office | D7: =_xlfn.XLOOKUP(A7,'EMPLOYEE MASTER DATA'!A7:A306,'EMPLOYEE MASTER DATA'!E7:E306) -> Receptionist | E7: =_xlfn.XLOOKUP(A7,'EMPLOYEE MASTER DATA'!A7:A306,'EMPLOYEE MASTER DATA'!F7:F306) -> 20500 | F7: =E7/24 -> 854.16667 | G7: 22 | H7: =_xlfn.XLOOKUP(A7,'MONTHLY ATTENDANCE SUMMARY'!A6:A305,'MONTHLY ATTENDANCE SUMMARY'!F6:F305) -> 1 | I7: =MIN(H7,1) -> 1 | J7: =MAX(H7-1,0) -> 0 | K7: =F7*(G7+I7+(J7*0.5)) -> 19645.833 | L7: =E7*12% -> 2460 | M7: =IF(K7>=21000,200,0) -> 0 | N7: =IF(K7<=21000,K7*0.75%,0) -> 147.34375 | O7: =K7-SUM(L7:N7) -> 17038.49
A8: EMP005 | B8: Naveen Kumar | C8: =_xlfn.XLOOKUP(A8,'EMPLOYEE MASTER DATA'!A8:A307,'EMPLOYEE MASTER DATA'!D8:D307) -> Front Office | D8: =_xlfn.XLOOKUP(A8,'EMPLOYEE MASTER DATA'!A8:A307,'EMPLOYEE MASTER DATA'!E8:E307) -> Front Office Executive | E8: =_xlfn.XLOOKUP(A8,'EMPLOYEE MASTER DATA'!A8:A307,'EMPLOYEE MASTER DATA'!F8:F307) -> 29000 | F8: =E8/24 -> 1208.3333 | G8: 18 | H8: =_xlfn.XLOOKUP(A8,'MONTHLY ATTENDANCE SUMMARY'!A7:A306,'MONTHLY ATTENDANCE SUMMARY'!F7:F306) -> 1 | I8: =MIN(H8,1) -> 1 | J8: =MAX(H8-1,0) -> 0 | K8: =F8*(G8+I8+(J8*0.5)) -> 22958.333 | L8: =E8*12% -> 3480 | M8: =IF(K8>=21000,200,0) -> 200 | N8: =IF(K8<=21000,K8*0.75%,0) -> 0 | O8: =K8-SUM(L8:N8) -> 19278.333
A9: EMP006 | B9: Karthik T | C9: =_xlfn.XLOOKUP(A9,'EMPLOYEE MASTER DATA'!A9:A308,'EMPLOYEE MASTER DATA'!D9:D308) -> Admin | D9: =_xlfn.XLOOKUP(A9,'EMPLOYEE MASTER DATA'!A9:A308,'EMPLOYEE MASTER DATA'!E9:E308) -> Admin Manager | E9: =_xlfn.XLOOKUP(A9,'EMPLOYEE MASTER DATA'!A9:A308,'EMPLOYEE MASTER DATA'!F9:F308) -> 53500 | F9: =E9/24 -> 2229.1667 | G9: 18 | H9: =_xlfn.XLOOKUP(A9,'MONTHLY ATTENDANCE SUMMARY'!A8:A307,'MONTHLY ATTENDANCE SUMMARY'!F8:F307) -> 2 | I9: =MIN(H9,1) -> 1 | J9: =MAX(H9-1,0) -> 1 | K9: =F9*(G9+I9+(J9*0.5)) -> 43468.75 | L9: =E9*12% -> 6420 | M9: =IF(K9>=21000,200,0) -> 200 | N9: =IF(K9<=21000,K9*0.75%,0) -> 0 | O9: =K9-SUM(L9:N9) -> 36848.75
A10: EMP007 | B10: Arun B | C10: =_xlfn.XLOOKUP(A10,'EMPLOYEE MASTER DATA'!A10:A309,'EMPLOYEE MASTER DATA'!D10:D309) -> Admin | D10: =_xlfn.XLOOKUP(A10,'EMPLOYEE MASTER DATA'!A10:A309,'EMPLOYEE MASTER DATA'!E10:E309) -> Office Coordinator | E10: =_xlfn.XLOOKUP(A10,'EMPLOYEE MASTER DATA'!A10:A309,'EMPLOYEE MASTER DATA'!F10:F309) -> 25500 | F10: =E10/24 -> 1062.5 | G10: 13 | H10: =_xlfn.XLOOKUP(A10,'MONTHLY ATTENDANCE SUMMARY'!A9:A308,'MONTHLY ATTENDANCE SUMMARY'!F9:F308) -> 1 | I10: =MIN(H10,1) -> 1 | J10: =MAX(H10-1,0) -> 0 | K10: =F10*(G10+I10+(J10*0.5)) -> 14875 | L10: =E10*12% -> 3060 | M10: =IF(K10>=21000,200,0) -> 0 | N10: =IF(K10<=21000,K10*0.75%,0) -> 111.5625 | O10: =K10-SUM(L10:N10) -> 11703.438
A11: EMP008 | B11: Sathish G | C11: =_xlfn.XLOOKUP(A11,'EMPLOYEE MASTER DATA'!A11:A310,'EMPLOYEE MASTER DATA'!D11:D310) -> Accounts | D11: =_xlfn.XLOOKUP(A11,'EMPLOYEE MASTER DATA'!A11:A310,'EMPLOYEE MASTER DATA'!E11:E310) -> Accountant | E11: =_xlfn.XLOOKUP(A11,'EMPLOYEE MASTER DATA'!A11:A310,'EMPLOYEE MASTER DATA'!F11:F310) -> 27500 | F11: =E11/24 -> 1145.8333 | G11: 18 | H11: =_xlfn.XLOOKUP(A11,'MONTHLY ATTENDANCE SUMMARY'!A10:A309,'MONTHLY ATTENDANCE SUMMARY'!F10:F309) -> 2 | I11: =MIN(H11,1) -> 1 | J11: =MAX(H11-1,0) -> 1 | K11: =F11*(G11+I11+(J11*0.5)) -> 22343.75 | L11: =E11*12% -> 3300 | M11: =IF(K11>=21000,200,0) -> 200 | N11: =IF(K11<=21000,K11*0.75%,0) -> 0 | O11: =K11-SUM(L11:N11) -> 18843.75
A12: EMP009 | B12: Yuvaraj Babu | C12: =_xlfn.XLOOKUP(A12,'EMPLOYEE MASTER DATA'!A12:A311,'EMPLOYEE MASTER DATA'!D12:D311) -> Sales | D12: =_xlfn.XLOOKUP(A12,'EMPLOYEE MASTER DATA'!A12:A311,'EMPLOYEE MASTER DATA'!E12:E311) -> Senior Sales Executive | E12: =_xlfn.XLOOKUP(A12,'EMPLOYEE MASTER DATA'!A12:A311,'EMPLOYEE MASTER DATA'!F12:F311) -> 43500 | F12: =E12/24 -> 1812.5 | G12: 22 | H12: =_xlfn.XLOOKUP(A12,'MONTHLY ATTENDANCE SUMMARY'!A11:A310,'MONTHLY ATTENDANCE SUMMARY'!F11:F310) -> 1 | I12: =MIN(H12,1) -> 1 | J12: =MAX(H12-1,0) -> 0 | K12: =F12*(G12+I12+(J12*0.5)) -> 41687.5 | L12: =E12*12% -> 5220 | M12: =IF(K12>=21000,200,0) -> 200 | N12: =IF(K12<=21000,K12*0.75%,0) -> 0 | O12: =K12-SUM(L12:N12) -> 36267.5
A13: EMP010 | B13: Sanjay G | C13: =_xlfn.XLOOKUP(A13,'EMPLOYEE MASTER DATA'!A13:A312,'EMPLOYEE MASTER DATA'!D13:D312) -> Procurement | D13: =_xlfn.XLOOKUP(A13,'EMPLOYEE MASTER DATA'!A13:A312,'EMPLOYEE MASTER DATA'!E13:E312) -> Buyer | E13: =_xlfn.XLOOKUP(A13,'EMPLOYEE MASTER DATA'!A13:A312,'EMPLOYEE MASTER DATA'!F13:F312) -> 45000 | F13: =E13/24 -> 1875 | G13: 22 | H13: =_xlfn.XLOOKUP(A13,'MONTHLY ATTENDANCE SUMMARY'!A12:A311,'MONTHLY ATTENDANCE SUMMARY'!F12:F311) -> 1 | I13: =MIN(H13,1) -> 1 | J13: =MAX(H13-1,0) -> 0 | K13: =F13*(G13+I13+(J13*0.5)) -> 43125 | L13: =E13*12% -> 5400 | M13: =IF(K13>=21000,200,0) -> 200 | N13: =IF(K13<=21000,K13*0.75%,0) -> 0 | O13: =K13-SUM(L13:N13) -> 37525
A14: EMP011 | B14: Vijay T | C14: =_xlfn.XLOOKUP(A14,'EMPLOYEE MASTER DATA'!A14:A313,'EMPLOYEE MASTER DATA'!D14:D313) -> Accounts | D14: =_xlfn.XLOOKUP(A14,'EMPLOYEE MASTER DATA'!A14:A313,'EMPLOYEE MASTER DATA'!E14:E313) -> Finance Executive | E14: =_xlfn.XLOOKUP(A14,'EMPLOYEE MASTER DATA'!A14:A313,'EMPLOYEE MASTER DATA'!F14:F313) -> 36000 | F14: =E14/24 -> 1500 | G14: 21 | H14: =_xlfn.XLOOKUP(A14,'MONTHLY ATTENDANCE SUMMARY'!A13:A312,'MONTHLY ATTENDANCE SUMMARY'!F13:F312) -> 1 | I14: =MIN(H14,1) -> 1 | J14: =MAX(H14-1,0) -> 0 | K14: =F14*(G14+I14+(J14*0.5)) -> 33000 | L14: =E14*12% -> 4320 | M14: =IF(K14>=21000,200,0) -> 200 | N14: =IF(K14<=21000,K14*0.75%,0) -> 0 | O14: =K14-SUM(L14:N14) -> 28480
A15: EMP012 | B15: Mohan M | C15: =_xlfn.XLOOKUP(A15,'EMPLOYEE MASTER DATA'!A15:A314,'EMPLOYEE MASTER DATA'!D15:D314) -> Admin | D15: =_xlfn.XLOOKUP(A15,'EMPLOYEE MASTER DATA'!A15:A314,'EMPLOYEE MASTER DATA'!E15:E314) -> Office Administrator | E15: =_xlfn.XLOOKUP(A15,'EMPLOYEE MASTER DATA'!A15:A314,'EMPLOYEE MASTER DATA'!F15:F314) -> 28000 | F15: =E15/24 -> 1166.6667 | G15: 19 | H15: =_xlfn.XLOOKUP(A15,'MONTHLY ATTENDANCE SUMMARY'!A14:A313,'MONTHLY ATTENDANCE SUMMARY'!F14:F313) -> 1 | I15: =MIN(H15,1) -> 1 | J15: =MAX(H15-1,0) -> 0 | K15: =F15*(G15+I15+(J15*0.5)) -> 23333.333 | L15: =E15*12% -> 3360 | M15: =IF(K15>=21000,200,0) -> 200 | N15: =IF(K15<=21000,K15*0.75%,0) -> 0 | O15: =K15-SUM(L15:N15) -> 19773.333
A16: EMP013 | B16: Madhan Selvam | C16: =_xlfn.XLOOKUP(A16,'EMPLOYEE MASTER DATA'!A16:A315,'EMPLOYEE MASTER DATA'!D16:D315) -> Accounts | D16: =_xlfn.XLOOKUP(A16,'EMPLOYEE MASTER DATA'!A16:A315,'EMPLOYEE MASTER DATA'!E16:E315) -> Senior Accountant | E16: =_xlfn.XLOOKUP(A16,'EMPLOYEE MASTER DATA'!A16:A315,'EMPLOYEE MASTER DATA'!F16:F315) -> 40500 | F16: =E16/24 -> 1687.5 | G16: 21 | H16: =_xlfn.XLOOKUP(A16,'MONTHLY ATTENDANCE SUMMARY'!A15:A314,'MONTHLY ATTENDANCE SUMMARY'!F15:F314) -> 2 | I16: =MIN(H16,1) -> 1 | J16: =MAX(H16-1,0) -> 1 | K16: =F16*(G16+I16+(J16*0.5)) -> 37968.75 | L16: =E16*12% -> 4860 | M16: =IF(K16>=21000,200,0) -> 200 | N16: =IF(K16<=21000,K16*0.75%,0) -> 0 | O16: =K16-SUM(L16:N16) -> 32908.75
... A303: EMP300 | B303: Ganesh Narayanan | C303: =_xlfn.XLOOKUP(A303,'EMPLOYEE MASTER DATA'!A303:A602,'EMPLOYEE MASTER DATA'!D303:D602) -> Maintenance | D303: =_xlfn.XLOOKUP(A303,'EMPLOYEE MASTER DATA'!A303:A602,'EMPLOYEE MASTER DATA'!E303:E602) -> Maintenance Supervisor | E303: =_xlfn.XLOOKUP(A303,'EMPLOYEE MASTER DATA'!A303:A602,'EMPLOYEE MASTER DATA'!F303:F602) -> 42000 | F303: =E303/24 -> 1750 | G303: 15 | H303: =_xlfn.XLOOKUP(A303,'MONTHLY ATTENDANCE SUMMARY'!A302:A601,'MONTHLY ATTENDANCE SUMMARY'!F302:F601) -> 2 | I303: =MIN(H303,1) -> 1 | J303: =MAX(H303-1,0) -> 1 | K303: =F303*(G303+I303+(J303*0.5)) -> 28875 | L303: =E303*12% -> 5040 | M303: =IF(K303>=21000,200,0) -> 200 | N303: =IF(K303<=21000,K303*0.75%,0) -> 0 | O303: =K303-SUM(L303:N303) -> 23635

Sheet SALARY SLIP
A1: NOVATECH SOLUTIONS PVT. LTD.
A3: SALARY SLIP - FEBRUARY 2026
A5: Employee ID | C5: EMP100
A6: Employee Name | C6: =_xlfn.XLOOKUP('SALARY SLIP'!C5,'MONTHLY ATTENDANCE SUMMARY'!A3:A302,'MONTHLY ATTENDANCE SUMMARY'!B3:B302," ") -> Deepak K
A7: Department | C7: =_xlfn.XLOOKUP('SALARY SLIP'!C5,'MONTHLY ATTENDANCE SUMMARY'!A3:A302,'MONTHLY ATTENDANCE SUMMARY'!C3:C302," ") -> Business Development
A8: Designation | C8: =_xlfn.XLOOKUP('SALARY SLIP'!C5,'EMPLOYEE MASTER DATA'!A4:A303,'EMPLOYEE MASTER DATA'!E4:E303," ") -> Growth Executive
A10: ATTENDANCE
A11: Present Days | C11: {=_xlfn.XLOOKUP(C5,PAYROLL!A4:A303,_xlfn.ANCHORARRAY(PAYROLL!G4)," ")} -> 20
A12: Approved Leave | C12: =_xlfn.XLOOKUP(C5,PAYROLL!A4:A303,PAYROLL!H4:H303," ") -> 1
A14: EARNINGS
A15: Basic Salary | F15: =_xlfn.XLOOKUP(C5,PAYROLL!A4:A303,PAYROLL!E4:E303," ") -> 44500
A16: Gross Salary | F16: =_xlfn.XLOOKUP(C5,PAYROLL!A4:A303,PAYROLL!K4:K303," ") -> 38937.5
A18: DEDUCTIONS
A19: PF | F19: =_xlfn.XLOOKUP('SALARY SLIP'!C5,PAYROLL!A4:A303,PAYROLL!L4:L303) -> 5340
A20: Professional Tax | F20: =_xlfn.XLOOKUP(C5,PAYROLL!A4:A303,PAYROLL!M4:M303,"-") -> 200
A21: ESI | F21: =_xlfn.XLOOKUP(C5,PAYROLL!A4:A303,PAYROLL!N4:N303,"-") -> 0
A23: Net Salary | F23: =_xlfn.XLOOKUP(C5,PAYROLL!A4:A303,PAYROLL!O4:O303) -> 33397.5
A24: This is a computer-generated salary slip.

Sheet PIVOTS
A1: DEPARTMENT - WISE EMPLOYEES | D1: DEPARTMENT - WISE GROSS SALARY
A2: Row Labels | B2: Count of Emp No | D2: Row Labels | E2: Sum of Gross Salary
A3: Accounts | B3: 32 | D3: Accounts | E3: 1318895.8
A4: Admin | B4: 26 | D4: Admin | E4: 685739.58
A5: Back End | B5: 22 | D5: Back End | E5: 667739.58
A6: Business Development | B6: 25 | D6: Business Development | E6: 1013500
A7: Customer Relationship | B7: 21 | D7: Customer Relationship | E7: 575104.17
A8: Front Office | B8: 22 | D8: Front Office | E8: 546937.5
A9: HR | B9: 16 | D9: HR | E9: 571093.75
A10: IT | B10: 19 | D10: IT | E10: 903697.92
A11: Maintenance | B11: 36 | D11: Maintenance | E11: 1546385.4
A12: Procurement | B12: 19 | D12: Procurement | E12: 742958.33
A13: Production | B13: 33 | D13: Production | E13: 1377614.6
A14: Sales | B14: 29 | D14: Sales | E14: 1067885.4
A15: Grand Total | B15: 300 | D15: Grand Total | E15: 11017552
A17: TOP 10 HIGHEST PAID EMPLOYEES | D17: ATTENDANCE DISTRIBUTION
A18: Name | B18: Sum of Gross Salary | D18: Status | E18: Percentage
A19: Vijay Babu | B19: 72656.25 | D19: Present | E19: ='HR MIS DASHBOARD'!D5 -> 0.83152778
A20: Ajay V | B20: 72875 | D20: Absent | E20: ='HR MIS DASHBOARD'!G5 -> 0.092274678
A21: Arun T | B21: 72947.917 | D21: Leave | E21: ='HR MIS DASHBOARD'!J5 -> 0.036712272
A22: Vignesh V | B22: 75708.333 | D22: Week Off | E22: =1-SUM(E19:E21) -> 0.039485272
A23: Aravind S | B23: 77083.333
A24: Sanjay Babu | B24: 79218.75
A25: Yogesh M | B25: 83854.167
A26: Bharath Kannan | B26: 83906.25
A27: Suresh Raj | B27: 88125
A28: Mohan K | B28: 88166.667

Sheet HR MIS DASHBOARD
A1: NOVATECH SOLUTIONS PVT. LTD.
A2: HR MIS DASHBOARD - FEBRUARY 2026
A3: TOTAL EMPLOYEES | D3: PRESENT PERCENTAGE | G3: ABSENT PERCETNAGE | J3: LEAVE PERCENTAGE
A5: =COUNTA('EMPLOYEE MASTER DATA'!A4:A303) -> 300 | D5: =AVERAGE('MONTHLY ATTENDANCE SUMMARY'!I3:I302) -> 0.83152778 | G5: =SUM('MONTHLY ATTENDANCE SUMMARY'!E3:E302)/(SUM('MONTHLY ATTENDANCE SUMMARY'!D3:D302)+SUM('MONTHLY ATTENDANCE SUMMARY'!E3:E302)+SUM('MONTHLY ATTENDANCE SUMMARY'!F3:F302)+SUM('MONTHLY ATTENDANCE SUMMARY'!G6:G302)) -> 0.092274678 | J5: =SUM('MONTHLY ATTENDANCE SUMMARY'!F3:F302)/(SUM('MONTHLY ATTENDANCE SUMMARY'!D3:D302)+SUM('MONTHLY ATTENDANCE SUMMARY'!E3:E302)+SUM('MONTHLY ATTENDANCE SUMMARY'!F3:IF302)+SUM('MONTHLY ATTENDANCE SUMMARY'!G6:G302)) -> 0.036712272
A7: GROSS PAYROLL | D7: NET PAYROLL | G7: AVG. GROSS SALARY | J7: PF TOTAL
A9: =SUM(PAYROLL!K4:K303) -> 11017552 | D9: =SUM(PAYROLL!O4:O303) -> 9460739.8 | G9: =AVERAGE(PAYROLL!K4:K303) -> 36725.174 | J9: =SUM(PAYROLL!L4:L303) -> 1497780

Sheet READ ME
B2: HR MIS DASHBOARD PROJECT
B4: Project Objective
B5: This project was developed to monitor and analyze HR data using Microsoft Excel. It provides insights into employee attendance, payroll, salary, and departmental statistics through an interactive dashboard.
B9: Key Features
B10: Total Employees KPI
B11: Present Percentage
B12: Absent Percentage
B13: Leave Percentage
B14: Gross Payroll
B15: Net Payroll
B16: Average Gross Salary
B17: PF Total
... B90: YUWARAJA G
